[{"Dataset": "/app/own/datasets/senadores", "Dataset Size": 856, "Model": "BERTopic", "Params": {"embedding_model": "all-mpnet-base-v2", "nr_topics": 5, "min_topic_size": 15, "verbose": true, "calculate_probabilities": false}, "Scores": {"cv": 0.4993086051963663, "npmi": 0.11959061051197321, "diversity": 0.92}, "Computation Time": 13.703169345855713, "Topics": [["hacer", "proyecto", "poder", "provincia", "él", "ley", "senador", "año", "presidente", "decir"], ["consideración", "uruguay", "palabra", "departamento", "villaguay", "senador", "gualeguaychú", "turno", "nogoyá", "diamante"], ["afirmativo", "sírvanse", "indicar", "resultar", "votar", "senador", "él", "formulado", "moción", "señor"], ["parlamentario", "labor", "acta", "votación", "bloque", "día", "número", "expediente", "alzado", "hoy"], ["secretaría", "reservado", "quedar", "asistencia", "tomar", "así", "hacer", "homenaje", "prosecretaría", "asentimiento"]]}, {"Dataset": "/app/own/datasets/senadores", "Dataset Size": 856, "Model": "BERTopic", "Params": {"embedding_model": "all-mpnet-base-v2", "nr_topics": 10, "min_topic_size": 15, "verbose": true, "calculate_probabilities": false}, "Scores": {"cv": 0.5157023627701524, "npmi": 0.1675225253828399, "diversity": 0.75}, "Computation Time": 6.134574890136719, "Topics": [["hacer", "poder", "proyecto", "provincia", "él", "ley", "año", "senador", "decir", "querer"], ["uruguay", "palabra", "departamento", "consideración", "villaguay", "senador", "turno", "homenaje", "victoria", "gualeguaychú"], ["secretaría", "reservado", "quedar", "asistencia", "tomar", "así", "homenaje", "hacer", "prosecretaría", "asentimiento"], ["acta", "votación", "parlamentario", "labor", "bloque", "número", "alzado", "día", "expediente", "mano"], ["afirmativo", "sírvanse", "indicar", "resultar", "él", "votar", "cuerpo", "formulado", "moción", "ingreso"], ["consideración", "federación", "nogoyá", "diamante", "gualeguaychú", "corresponder", "lista", "asunto", "nuevamente", "turno"], ["quedar", "pasar", "aprobado", "revisión", "honorable", "diputado", "sancionado", "promulgación", "cámara", "ejecutivo"], ["tratado", "tabla", "solicitar", "presidente", "señora", "proyecto", "señor", "colón", "tratamiento", "alcanzado"], ["afirmativo", "tercio", "senador", "voto", "formulado", "presente", "moción", "votar", "sírvanse", "dos"], ["diamante", "solicitar", "solicitar", "solicitar", "solicitar", "solicitar", "solicitar", "solicitar", "solicitar", "solicitar"]]}, {"Dataset": "/app/own/datasets/senadores", "Dataset Size": 856, "Model": "BERTopic", "Params": {"embedding_model": "all-mpnet-base-v2", "nr_topics": 15, "min_topic_size": 15, "verbose": true, "calculate_probabilities": false}, "Scores": {"cv": 0.5577357447382761, "npmi": 0.20789170664848644, "diversity": 0.6333333333333333}, "Computation Time": 6.294156789779663, "Topics": [["hacer", "poder", "provincia", "proyecto", "él", "ley", "año", "decir", "senador", "querer"], ["secretaría", "reservado", "quedar", "asistencia", "tomar", "así", "homenaje", "hacer", "prosecretaría", "asentimiento"], ["villaguay", "victoria", "consideración", "gualeguaychú", "salvador", "palabra", "isla", "sar", "departamento", "senador"], ["tratado", "tabla", "solicitar", "presidente", "señora", "proyecto", "señor", "colón", "tratamiento", "alcanzado"], ["palabra", "departamento", "turno", "senador", "consideración", "uruguay", "homenaje", "federal", "feliciano", "paz"], ["afirmativo", "tercio", "voto", "senador", "formulado", "presente", "moción", "votar", "sírvanse", "dos"], ["acta", "número", "expediente", "votación", "proyecto", "parlamentario", "labor", "comunicación", "bloque", "declaración"], ["consideración", "nogoyá", "diamante", "gualeguaychú", "nuevamente", "corresponder", "asunto", "lista", "gualeguay", "turno"], ["afirmativo", "sírvanse", "indicar", "resultar", "cuerpo", "consideración", "vergaro", "solicitud", "él", "ingreso"], ["parlamentario", "labor", "leído", "desarrollado", "siguiente", "conformar", "alzado", "mano", "votación", "tratamiento"], ["sancionado", "promulgación", "quedar", "ejecutivo", "pasar", "poder", "orden", "pertinente", "próximo", "consecuencia"], ["diamante", "solicitar", "solicitar", "solicitar", "solicitar", "solicitar", "solicitar", "solicitar", "solicitar", "solicitar"], ["uruguay", "solicitar", "solicitar", "solicitar", "solicitar", "solicitar", "solicitar", "solicitar", "solicitar", "solicitar"], ["afirmativo", "sírvanse", "indicar", "votar", "resultar", "él", "formulado", "moción", "oliva", "ingreso"], ["revisión", "aprobado", "honorable", "diputado", "cámara", "quedar", "pasar", "devolver", "plan", "orden"]]}, {"Dataset": "/app/own/datasets/senadores", "Dataset Size": 856, "Model": "BERTopic", "Params": {"embedding_model": "all-mpnet-base-v2", "nr_topics": 20, "min_topic_size": 15, "verbose": true, "calculate_probabilities": false}, "Scores": {"cv": 0.5600521025762478, "npmi": 0.22943457551271126, "diversity": 0.5882352941176471}, "Computation Time": 11.56976842880249, "Topics": [["diamante", "solicitar", "solicitar", "solicitar", "solicitar", "solicitar", "solicitar", "solicitar", "solicitar", "solicitar"], ["uruguay", "solicitar", "solicitar", "solicitar", "solicitar", "solicitar", "solicitar", "solicitar", "solicitar", "solicitar"], ["afirmativo", "sírvanse", "indicar", "votar", "resultar", "él", "formulado", "moción", "oliva", "ingreso"], ["afirmativo", "sírvanse", "indicar", "resultar", "cuerpo", "consideración", "vergaro", "solicitud", "él", "ingreso"], ["afirmativo", "requerir", "tercio", "voto", "senador", "formulado", "presente", "moción", "votar", "sírvanse"], ["asistencia", "tomar", "así", "secretaría", "hacer", "asentimiento", "verónico", "tarde", "bienvenida", "berisso"], ["reservado", "quedar", "secretaría", "homenaje", "prosecretaría", "asistencia", "tomar", "así", "hacer", "solicitar"], ["afirmativo", "tercio", "voto", "formulado", "senador", "presente", "moción", "señor", "votar", "sírvanse"], ["revisión", "aprobado", "honorable", "diputado", "cámara", "quedar", "pasar", "devolver", "plan", "orden"], ["tratado", "tabla", "solicitar", "presidente", "señora", "proyecto", "señor", "colón", "tratamiento", "alcanzado"], ["consideración", "federación", "nogoyá", "diamante", "gualeguaychú", "corresponder", "lista", "asunto", "nuevamente", "turno"], ["acta", "entrado", "resultado", "votación", "parlamentario", "aprobado", "labor", "asunto", "día", "hoy"], ["parlamentario", "labor", "leído", "desarrollado", "siguiente", "conformar", "alzado", "mano", "votación", "tratamiento"], ["palabra", "departamento", "consideración", "villaguay", "senador", "turno", "victoria", "homenaje", "gualeguaychú", "uruguay"], ["sancionado", "promulgación", "quedar", "ejecutivo", "pasar", "poder", "orden", "pertinente", "próximo", "consecuencia"], ["número", "expediente", "acta", "proyecto", "comunicación", "bloque", "declaración", "pendiente", "acordar", "modo"], ["hacer", "poder", "proyecto", "provincia", "él", "ley", "año", "decir", "senador", "querer"]]}, {"Dataset": "/app/own/datasets/senadores", "Dataset Size": 856, "Model": "BERTopic", "Params": {"embedding_model": "all-mpnet-base-v2", "nr_topics": 25, "min_topic_size": 15, "verbose": true, "calculate_probabilities": false}, "Scores": {"cv": 0.5502772318987484, "npmi": 0.20949094916935249, "diversity": 0.5888888888888889}, "Computation Time": 9.549397230148315, "Topics": [["diamante", "solicitar", "solicitar", "solicitar", "solicitar", "solicitar", "solicitar", "solicitar", "solicitar", "solicitar"], ["uruguay", "solicitar", "solicitar", "solicitar", "solicitar", "solicitar", "solicitar", "solicitar", "solicitar", "solicitar"], ["afirmativo", "sírvanse", "indicar", "resultar", "cuerpo", "consideración", "vergaro", "solicitud", "él", "ingreso"], ["afirmativo", "requerir", "tercio", "voto", "senador", "formulado", "presente", "moción", "votar", "sírvanse"], ["asistencia", "tomar", "así", "secretaría", "hacer", "asentimiento", "verónico", "tarde", "bienvenida", "berisso"], ["reservado", "quedar", "secretaría", "homenaje", "prosecretaría", "asistencia", "tomar", "así", "hacer", "solicitar"], ["afirmativo", "sírvanse", "indicar", "votar", "resultar", "él", "formulado", "moción", "oliva", "ingreso"], ["afirmativo", "tercio", "voto", "formulado", "senador", "presente", "moción", "señor", "señoro", "votar"], ["tratado", "tabla", "solicitar", "presidente", "señora", "proyecto", "señor", "colón", "tratamiento", "alcanzado"], ["acta", "entrado", "resultado", "parlamentario", "labor", "votación", "aprobado", "asunto", "día", "hoy"], ["parlamentario", "labor", "leído", "desarrollado", "siguiente", "conformar", "alzado", "mano", "votación", "tratamiento"], ["revisión", "aprobado", "honorable", "diputado", "cámara", "quedar", "pasar", "devolver", "plan", "orden"], ["consideración", "federación", "nogoyá", "diamante", "gualeguaychú", "corresponder", "lista", "asunto", "nuevamente", "turno"], ["villaguay", "victoria", "consideración", "gualeguaychú", "salvador", "palabra", "isla", "sar", "departamento", "senador"], ["palabra", "departamento", "turno", "senador", "consideración", "homenaje", "uruguay", "federal", "feliciano", "paz"], ["sancionado", "promulgación", "quedar", "ejecutivo", "pasar", "poder", "pertinente", "aprobado", "comunicación", "funcionar"], ["número", "expediente", "acta", "proyecto", "comunicación", "bloque", "declaración", "pendiente", "acordar", "modo"], ["hacer", "poder", "provincia", "proyecto", "él", "ley", "año", "decir", "senador", "querer"]]}, {"Dataset": "/app/own/datasets/senadores", "Dataset Size": 856, "Model": "BERTopic", "Params": {"embedding_model": "all-mpnet-base-v2", "nr_topics": 30, "min_topic_size": 15, "verbose": true, "calculate_probabilities": false}, "Scores": {"cv": 0.5502772318987484, "npmi": 0.20949094916935249, "diversity": 0.5888888888888889}, "Computation Time": 6.983012437820435, "Topics": [["diamante", "solicitar", "solicitar", "solicitar", "solicitar", "solicitar", "solicitar", "solicitar", "solicitar", "solicitar"], ["uruguay", "solicitar", "solicitar", "solicitar", "solicitar", "solicitar", "solicitar", "solicitar", "solicitar", "solicitar"], ["afirmativo", "requerir", "tercio", "voto", "senador", "formulado", "presente", "moción", "votar", "sírvanse"], ["afirmativo", "sírvanse", "indicar", "resultar", "cuerpo", "consideración", "vergaro", "solicitud", "él", "ingreso"], ["asistencia", "tomar", "así", "secretaría", "hacer", "asentimiento", "verónico", "tarde", "bienvenida", "berisso"], ["reservado", "quedar", "secretaría", "homenaje", "prosecretaría", "asistencia", "tomar", "así", "hacer", "solicitar"], ["acta", "entrado", "resultado", "parlamentario", "labor", "votación", "aprobado", "asunto", "día", "hoy"], ["parlamentario", "labor", "leído", "desarrollado", "siguiente", "conformar", "alzado", "mano", "votación", "tratamiento"], ["afirmativo", "sírvanse", "indicar", "votar", "resultar", "él", "formulado", "moción", "oliva", "ingreso"], ["afirmativo", "tercio", "voto", "formulado", "senador", "presente", "moción", "señor", "señoro", "votar"], ["tratado", "tabla", "solicitar", "presidente", "señora", "proyecto", "señor", "colón", "tratamiento", "alcanzado"], ["revisión", "aprobado", "honorable", "diputado", "cámara", "quedar", "pasar", "devolver", "plan", "orden"], ["consideración", "federación", "nogoyá", "diamante", "gualeguaychú", "corresponder", "lista", "asunto", "nuevamente", "turno"], ["palabra", "departamento", "turno", "senador", "consideración", "homenaje", "uruguay", "federal", "feliciano", "paz"], ["villaguay", "victoria", "consideración", "gualeguaychú", "salvador", "palabra", "isla", "sar", "departamento", "senador"], ["sancionado", "promulgación", "quedar", "ejecutivo", "pasar", "poder", "pertinente", "aprobado", "comunicación", "funcionar"], ["número", "expediente", "acta", "proyecto", "comunicación", "bloque", "declaración", "pendiente", "acordar", "modo"], ["hacer", "poder", "provincia", "proyecto", "él", "ley", "año", "decir", "senador", "querer"]]}, {"Dataset": "/app/own/datasets/senadores", "Dataset Size": 856, "Model": "BERTopic", "Params": {"embedding_model": "all-mpnet-base-v2", "nr_topics": 35, "min_topic_size": 15, "verbose": true, "calculate_probabilities": false}, "Scores": {"cv": 0.5624550349990858, "npmi": 0.2266747822962836, "diversity": 0.5823529411764706}, "Computation Time": 5.27727746963501, "Topics": [["uruguay", "solicitar", "solicitar", "solicitar", "solicitar", "solicitar", "solicitar", "solicitar", "solicitar", "solicitar"], ["diamante", "solicitar", "solicitar", "solicitar", "solicitar", "solicitar", "solicitar", "solicitar", "solicitar", "solicitar"], ["afirmativo", "requerir", "tercio", "voto", "senador", "formulado", "presente", "moción", "votar", "sírvanse"], ["afirmativo", "tercio", "voto", "formulado", "senador", "presente", "moción", "señor", "votar", "sírvanse"], ["afirmativo", "sírvanse", "indicar", "votar", "resultar", "él", "formulado", "moción", "oliva", "ingreso"], ["consideración", "federación", "nogoyá", "diamante", "gualeguaychú", "corresponder", "lista", "asunto", "nuevamente", "turno"], ["revisión", "aprobado", "honorable", "diputado", "cámara", "quedar", "pasar", "devolver", "plan", "orden"], ["tratado", "tabla", "solicitar", "presidente", "señora", "proyecto", "señor", "colón", "tratamiento", "alcanzado"], ["parlamentario", "labor", "leído", "desarrollado", "siguiente", "conformar", "alzado", "mano", "votación", "tratamiento"], ["acta", "entrado", "resultado", "parlamentario", "labor", "votación", "aprobado", "asunto", "día", "hoy"], ["sancionado", "promulgación", "quedar", "ejecutivo", "pasar", "poder", "pertinente", "aprobado", "comunicación", "funcionar"], ["palabra", "departamento", "consideración", "villaguay", "senador", "turno", "victoria", "homenaje", "gualeguaychú", "uruguay"], ["número", "expediente", "acta", "proyecto", "comunicación", "bloque", "declaración", "pendiente", "acordar", "modo"], ["hacer", "poder", "proyecto", "provincia", "él", "ley", "año", "decir", "senador", "querer"], ["afirmativo", "sírvanse", "indicar", "resultar", "cuerpo", "consideración", "vergaro", "solicitud", "él", "ingreso"], ["asistencia", "tomar", "así", "secretaría", "hacer", "asentimiento", "verónico", "tarde", "bienvenida", "berisso"], ["reservado", "quedar", "secretaría", "homenaje", "prosecretaría", "asistencia", "tomar", "así", "hacer", "solicitar"]]}, {"Dataset": "/app/own/datasets/senadores", "Dataset Size": 856, "Model": "BERTopic", "Params": {"embedding_model": "all-mpnet-base-v2", "nr_topics": 40, "min_topic_size": 15, "verbose": true, "calculate_probabilities": false}, "Scores": {"cv": 0.5624426633736643, "npmi": 0.2243260757809115, "diversity": 0.5882352941176471}, "Computation Time": 5.608083009719849, "Topics": [["uruguay", "solicitar", "solicitar", "solicitar", "solicitar", "solicitar", "solicitar", "solicitar", "solicitar", "solicitar"], ["diamante", "solicitar", "solicitar", "solicitar", "solicitar", "solicitar", "solicitar", "solicitar", "solicitar", "solicitar"], ["parlamentario", "labor", "leído", "desarrollado", "siguiente", "conformar", "alzado", "mano", "votación", "tratamiento"], ["acta", "entrado", "resultado", "parlamentario", "labor", "votación", "aprobado", "asunto", "día", "hoy"], ["afirmativo", "sírvanse", "indicar", "resultar", "cuerpo", "consideración", "vergaro", "solicitud", "él", "ingreso"], ["afirmativo", "requerir", "tercio", "voto", "senador", "formulado", "presente", "moción", "votar", "sírvanse"], ["asistencia", "tomar", "así", "secretaría", "hacer", "asentimiento", "verónico", "tarde", "bienvenida", "berisso"], ["reservado", "quedar", "secretaría", "homenaje", "prosecretaría", "asistencia", "tomar", "así", "hacer", "solicitar"], ["afirmativo", "tercio", "voto", "senador", "formulado", "presente", "señor", "moción", "votar", "señoro"], ["afirmativo", "sírvanse", "indicar", "resultar", "votar", "formulado", "él", "moción", "oliva", "ingreso"], ["revisión", "aprobado", "honorable", "diputado", "cámara", "quedar", "pasar", "devolver", "plan", "orden"], ["tratado", "tabla", "solicitar", "presidente", "señora", "proyecto", "señor", "colón", "tratamiento", "alcanzado"], ["consideración", "federación", "nogoyá", "diamante", "gualeguaychú", "corresponder", "lista", "asunto", "nuevamente", "turno"], ["palabra", "departamento", "consideración", "villaguay", "senador", "turno", "victoria", "homenaje", "gualeguaychú", "uruguay"], ["sancionado", "promulgación", "quedar", "ejecutivo", "pasar", "poder", "pertinente", "aprobado", "comunicación", "funcionar"], ["número", "expediente", "acta", "proyecto", "comunicación", "bloque", "declaración", "pendiente", "acordar", "modo"], ["hacer", "poder", "proyecto", "provincia", "él", "ley", "año", "decir", "senador", "querer"]]}, {"Dataset": "/app/own/datasets/senadores", "Dataset Size": 856, "Model": "BERTopic", "Params": {"embedding_model": "all-mpnet-base-v2", "nr_topics": 45, "min_topic_size": 15, "verbose": true, "calculate_probabilities": false}, "Scores": {"cv": 0.5674828785278748, "npmi": 0.22324984752328123, "diversity": 0.5823529411764706}, "Computation Time": 5.28387975692749, "Topics": [["uruguay", "solicitar", "solicitar", "solicitar", "solicitar", "solicitar", "solicitar", "solicitar", "solicitar", "solicitar"], ["diamante", "solicitar", "solicitar", "solicitar", "solicitar", "solicitar", "solicitar", "solicitar", "solicitar", "solicitar"], ["afirmativo", "sírvanse", "indicar", "resultar", "cuerpo", "consideración", "vergaro", "solicitud", "él", "ingreso"], ["afirmativo", "requerir", "tercio", "voto", "senador", "formulado", "presente", "moción", "votar", "sírvanse"], ["asistencia", "tomar", "así", "secretaría", "hacer", "asentimiento", "verónico", "tarde", "bienvenida", "berisso"], ["reservado", "quedar", "secretaría", "homenaje", "prosecretaría", "asistencia", "tomar", "así", "hacer", "solicitar"], ["tratado", "tabla", "solicitar", "presidente", "señora", "proyecto", "señor", "colón", "tratamiento", "alcanzado"], ["afirmativo", "tercio", "voto", "formulado", "senador", "presente", "moción", "señor", "votar", "sírvanse"], ["afirmativo", "sírvanse", "indicar", "votar", "resultar", "él", "formulado", "moción", "oliva", "ingreso"], ["parlamentario", "labor", "leído", "desarrollado", "siguiente", "conformar", "alzado", "mano", "votación", "tratamiento"], ["acta", "entrado", "resultado", "parlamentario", "labor", "votación", "aprobado", "asunto", "día", "hoy"], ["revisión", "aprobado", "honorable", "diputado", "cámara", "quedar", "pasar", "devolver", "plan", "orden"], ["consideración", "nogoyá", "diamante", "gualeguaychú", "nuevamente", "corresponder", "asunto", "lista", "gualeguay", "turno"], ["sancionado", "promulgación", "quedar", "ejecutivo", "pasar", "poder", "pertinente", "aprobado", "comunicación", "funcionar"], ["palabra", "departamento", "consideración", "villaguay", "senador", "turno", "victoria", "homenaje", "gualeguaychú", "uruguay"], ["número", "expediente", "acta", "proyecto", "comunicación", "bloque", "declaración", "pendiente", "acordar", "modo"], ["hacer", "poder", "proyecto", "provincia", "él", "ley", "año", "decir", "senador", "querer"]]}, {"Dataset": "/app/own/datasets/senadores", "Dataset Size": 856, "Model": "BERTopic", "Params": {"embedding_model": "all-mpnet-base-v2", "nr_topics": 50, "min_topic_size": 15, "verbose": true, "calculate_probabilities": false}, "Scores": {"cv": 0.5624550349990859, "npmi": 0.2266747822962836, "diversity": 0.5823529411764706}, "Computation Time": 5.701781511306763, "Topics": [["diamante", "solicitar", "solicitar", "solicitar", "solicitar", "solicitar", "solicitar", "solicitar", "solicitar", "solicitar"], ["asistencia", "tomar", "así", "secretaría", "hacer", "asentimiento", "verónico", "tarde", "bienvenida", "berisso"], ["reservado", "quedar", "secretaría", "homenaje", "prosecretaría", "asistencia", "tomar", "así", "hacer", "solicitar"], ["uruguay", "solicitar", "solicitar", "solicitar", "solicitar", "solicitar", "solicitar", "solicitar", "solicitar", "solicitar"], ["afirmativo", "sírvanse", "indicar", "resultar", "cuerpo", "consideración", "vergaro", "solicitud", "él", "ingreso"], ["tratado", "tabla", "solicitar", "presidente", "señora", "proyecto", "señor", "colón", "tratamiento", "alcanzado"], ["afirmativo", "requerir", "tercio", "voto", "senador", "formulado", "presente", "moción", "votar", "sírvanse"], ["afirmativo", "tercio", "voto", "formulado", "senador", "presente", "moción", "señor", "votar", "sírvanse"], ["afirmativo", "sírvanse", "indicar", "votar", "resultar", "él", "formulado", "moción", "oliva", "ingreso"], ["acta", "entrado", "resultado", "parlamentario", "labor", "votación", "aprobado", "asunto", "día", "hoy"], ["parlamentario", "labor", "leído", "desarrollado", "siguiente", "conformar", "alzado", "mano", "votación", "tratamiento"], ["consideración", "federación", "nogoyá", "diamante", "gualeguaychú", "corresponder", "lista", "asunto", "nuevamente", "turno"], ["revisión", "aprobado", "honorable", "diputado", "cámara", "quedar", "pasar", "devolver", "plan", "orden"], ["palabra", "departamento", "consideración", "villaguay", "senador", "turno", "homenaje", "victoria", "gualeguaychú", "uruguay"], ["sancionado", "promulgación", "quedar", "ejecutivo", "pasar", "poder", "pertinente", "aprobado", "comunicación", "funcionar"], ["número", "expediente", "acta", "proyecto", "comunicación", "bloque", "declaración", "pendiente", "acordar", "modo"], ["hacer", "poder", "provincia", "proyecto", "él", "ley", "año", "decir", "senador", "querer"]]}]