[{"Dataset": "/app/own/datasets/senadores", "Dataset Size": 856, "Model": "BERTopic", "Params": {"embedding_model": "all-mpnet-base-v2", "nr_topics": 5, "min_topic_size": 15, "verbose": true, "calculate_probabilities": false}, "Scores": {"cv": 0.4104728498752387, "npmi": 0.0574940119518921, "diversity": 0.88}, "Computation Time": 5.7571702003479, "Topics": [["hacer", "proyecto", "poder", "provincia", "él", "ley", "senador", "año", "presidente", "decir"], ["uruguay", "palabra", "departamento", "consideración", "villaguay", "senador", "turno", "homenaje", "victoria", "gualeguaychú"], ["afirmativo", "sírvanse", "indicar", "resultar", "votar", "senador", "él", "formulado", "moción", "señor"], ["quedar", "secretaría", "reservado", "pasar", "aprobado", "revisión", "asistencia", "honorable", "diputado", "sancionado"], ["diamante", "consideración", "federación", "nogoyá", "gualeguaychú", "corresponder", "asunto", "lista", "nuevamente", "turno"]]}, {"Dataset": "/app/own/datasets/senadores", "Dataset Size": 856, "Model": "BERTopic", "Params": {"embedding_model": "all-mpnet-base-v2", "nr_topics": 10, "min_topic_size": 15, "verbose": true, "calculate_probabilities": false}, "Scores": {"cv": 0.4082762688714049, "npmi": 0.07406899987448774, "diversity": 0.72}, "Computation Time": 5.656735420227051, "Topics": [["hacer", "poder", "proyecto", "provincia", "él", "ley", "año", "senador", "decir", "querer"], ["senador", "palabra", "departamento", "afirmativo", "consideración", "villaguay", "tercio", "señor", "voto", "formulado"], ["quedar", "afirmativo", "reservado", "secretaría", "requerir", "tercio", "senador", "acta", "voto", "formulado"], ["tratado", "tabla", "solicitar", "presidente", "afirmativo", "señora", "informado", "proyecto", "votar", "sírvanse"], ["parlamentario", "labor", "leído", "honorable", "desarrollado", "revisión", "aprobado", "siguiente", "diputado", "conformar"], ["diamante", "asistencia", "tomar", "así", "secretaría", "hacer", "asentimiento", "verónico", "tarde", "bienvenida"], ["consideración", "federación", "nogoyá", "diamante", "gualeguaychú", "corresponder", "lista", "asunto", "nuevamente", "turno"], ["número", "expediente", "comunicación", "acta", "proyecto", "bloque", "declaración", "pendiente", "acordar", "modo"], ["afirmativo", "sírvanse", "indicar", "resultar", "cuerpo", "consideración", "vergaro", "solicitud", "él", "señor"], ["uruguay", "solicitar", "solicitar", "solicitar", "solicitar", "solicitar", "solicitar", "solicitar", "solicitar", "solicitar"]]}, {"Dataset": "/app/own/datasets/senadores", "Dataset Size": 856, "Model": "BERTopic", "Params": {"embedding_model": "all-mpnet-base-v2", "nr_topics": 15, "min_topic_size": 15, "verbose": true, "calculate_probabilities": false}, "Scores": {"cv": 0.5689777489531177, "npmi": 0.22697755341701414, "diversity": 0.6466666666666666}, "Computation Time": 9.676295280456543, "Topics": [["hacer", "poder", "provincia", "año", "él", "proyecto", "decir", "querer", "ir", "ley"], ["palabra", "departamento", "consideración", "villaguay", "senador", "turno", "homenaje", "victoria", "gualeguaychú", "uruguay"], ["secretaría", "reservado", "quedar", "asistencia", "tomar", "así", "homenaje", "hacer", "prosecretaría", "asentimiento"], ["afirmativo", "sírvanse", "indicar", "resultar", "él", "votar", "cuerpo", "formulado", "moción", "ingreso"], ["consideración", "federación", "nogoyá", "diamante", "gualeguaychú", "corresponder", "lista", "asunto", "nuevamente", "turno"], ["quedar", "aprobado", "pasar", "revisión", "honorable", "diputado", "sancionado", "promulgación", "cámara", "ejecutivo"], ["tratado", "tabla", "solicitar", "presidente", "señora", "proyecto", "señor", "colón", "tratamiento", "alcanzado"], ["afirmativo", "tercio", "voto", "senador", "formulado", "presente", "moción", "votar", "sírvanse", "dos"], ["acta", "número", "expediente", "votación", "proyecto", "parlamentario", "labor", "comunicación", "bloque", "declaración"], ["legislación", "ley", "comisión", "general", "expediente", "despacho", "revisión", "proyecto", "ingreso", "ejecutivo"], ["parlamentario", "labor", "leído", "desarrollado", "siguiente", "conformar", "alzado", "mano", "votación", "tratamiento"], ["senador", "señor", "izar", "bandera", "departamento", "ordinario", "presencia", "sesión", "período", "abierto"], ["presidente", "señora", "ausencia", "señor", "justificar", "senador", "próximo", "sesión", "cosso", "formular"], ["diamante", "solicitar", "solicitar", "solicitar", "solicitar", "solicitar", "solicitar", "solicitar", "solicitar", "solicitar"], ["uruguay", "solicitar", "solicitar", "solicitar", "solicitar", "solicitar", "solicitar", "solicitar", "solicitar", "solicitar"]]}, {"Dataset": "/app/own/datasets/senadores", "Dataset Size": 856, "Model": "BERTopic", "Params": {"embedding_model": "all-mpnet-base-v2", "nr_topics": 20, "min_topic_size": 15, "verbose": true, "calculate_probabilities": false}, "Scores": {"cv": 0.5517390913478437, "npmi": 0.21385092473874856, "diversity": 0.5941176470588235}, "Computation Time": 5.16796612739563, "Topics": [["afirmativo", "requerir", "tercio", "voto", "senador", "formulado", "presente", "moción", "votar", "sírvanse"], ["uruguay", "solicitar", "solicitar", "solicitar", "solicitar", "solicitar", "solicitar", "solicitar", "solicitar", "solicitar"], ["diamante", "solicitar", "solicitar", "solicitar", "solicitar", "solicitar", "solicitar", "solicitar", "solicitar", "solicitar"], ["tratado", "tabla", "solicitar", "presidente", "señora", "proyecto", "señor", "colón", "tratamiento", "alcanzado"], ["afirmativo", "sírvanse", "indicar", "resultar", "cuerpo", "consideración", "vergaro", "solicitud", "él", "ingreso"], ["afirmativo", "sírvanse", "indicar", "votar", "resultar", "él", "formulado", "moción", "oliva", "ingreso"], ["afirmativo", "tercio", "voto", "formulado", "senador", "presente", "moción", "señor", "votar", "sírvanse"], ["leído", "desarrollado", "siguiente", "conformar", "alzado", "mano", "votación", "tratamiento", "poner", "acordado"], ["asunto", "parlamentario", "labor", "acta", "entrado", "resultado", "listo", "votación", "aprobado", "establecido"], ["consideración", "nogoyá", "diamante", "gualeguaychú", "nuevamente", "corresponder", "asunto", "lista", "gualeguay", "turno"], ["revisión", "aprobado", "honorable", "diputado", "cámara", "quedar", "pasar", "devolver", "plan", "orden"], ["palabra", "consideración", "departamento", "villaguay", "turno", "federación", "senador", "victoria", "homenaje", "gualeguaychú"], ["número", "expediente", "acta", "proyecto", "comunicación", "bloque", "declaración", "pendiente", "acordar", "modo"], ["sancionado", "promulgación", "quedar", "ejecutivo", "pasar", "poder", "pertinente", "aprobado", "comunicación", "orden"], ["hacer", "poder", "proyecto", "provincia", "él", "ley", "año", "decir", "senador", "querer"], ["reservado", "quedar", "secretaría", "homenaje", "prosecretaría", "asistencia", "tomar", "así", "hacer", "solicitar"], ["asistencia", "tomar", "así", "secretaría", "hacer", "asentimiento", "verónico", "tarde", "bienvenida", "berisso"]]}, {"Dataset": "/app/own/datasets/senadores", "Dataset Size": 856, "Model": "BERTopic", "Params": {"embedding_model": "all-mpnet-base-v2", "nr_topics": 25, "min_topic_size": 15, "verbose": true, "calculate_probabilities": false}, "Scores": {"cv": 0.5365059237033507, "npmi": 0.19411240070877886, "diversity": 0.5823529411764706}, "Computation Time": 4.8322227001190186, "Topics": [["uruguay", "solicitar", "solicitar", "solicitar", "solicitar", "solicitar", "solicitar", "solicitar", "solicitar", "solicitar"], ["diamante", "informado", "afirmativo", "votar", "sírvanse", "indicar", "resultar", "secretaría", "él", "solicitar"], ["tratado", "tabla", "solicitar", "presidente", "señora", "proyecto", "señor", "colón", "tratamiento", "alcanzado"], ["afirmativo", "sírvanse", "indicar", "resultar", "cuerpo", "consideración", "vergaro", "solicitud", "él", "ingreso"], ["afirmativo", "requerir", "tercio", "voto", "senador", "formulado", "presente", "moción", "votar", "sírvanse"], ["asistencia", "tomar", "así", "secretaría", "hacer", "asentimiento", "verónico", "tarde", "bienvenida", "berisso"], ["reservado", "quedar", "secretaría", "homenaje", "prosecretaría", "asistencia", "tomar", "así", "hacer", "solicitar"], ["afirmativo", "sírvanse", "indicar", "votar", "resultar", "él", "formulado", "moción", "oliva", "ingreso"], ["afirmativo", "tercio", "voto", "formulado", "senador", "presente", "moción", "señor", "votar", "sírvanse"], ["acta", "entrado", "resultado", "parlamentario", "labor", "votación", "aprobado", "asunto", "día", "hoy"], ["parlamentario", "labor", "leído", "desarrollado", "siguiente", "conformar", "alzado", "mano", "votación", "tratamiento"], ["consideración", "nogoyá", "diamante", "gualeguaychú", "corresponder", "lista", "asunto", "nuevamente", "turno", "entrado"], ["revisión", "aprobado", "honorable", "diputado", "cámara", "quedar", "pasar", "devolver", "plan", "orden"], ["sancionado", "promulgación", "quedar", "ejecutivo", "pasar", "poder", "pertinente", "aprobado", "comunicación", "funcionar"], ["palabra", "departamento", "consideración", "villaguay", "senador", "turno", "victoria", "homenaje", "gualeguaychú", "uruguay"], ["número", "expediente", "acta", "proyecto", "comunicación", "bloque", "declaración", "pendiente", "acordar", "modo"], ["hacer", "poder", "proyecto", "provincia", "él", "ley", "año", "decir", "senador", "querer"]]}, {"Dataset": "/app/own/datasets/senadores", "Dataset Size": 856, "Model": "BERTopic", "Params": {"embedding_model": "all-mpnet-base-v2", "nr_topics": 30, "min_topic_size": 15, "verbose": true, "calculate_probabilities": false}, "Scores": {"cv": 0.5543848810370265, "npmi": 0.2129479386605276, "diversity": 0.5941176470588235}, "Computation Time": 4.838181018829346, "Topics": [["diamante", "solicitar", "solicitar", "solicitar", "solicitar", "solicitar", "solicitar", "solicitar", "solicitar", "solicitar"], ["uruguay", "solicitar", "solicitar", "solicitar", "solicitar", "solicitar", "solicitar", "solicitar", "solicitar", "solicitar"], ["asistencia", "tomar", "así", "secretaría", "hacer", "asentimiento", "verónico", "tarde", "bienvenida", "berisso"], ["reservado", "quedar", "secretaría", "homenaje", "prosecretaría", "asistencia", "tomar", "así", "hacer", "solicitar"], ["afirmativo", "sírvanse", "indicar", "resultar", "cuerpo", "consideración", "vergaro", "solicitud", "él", "ingreso"], ["afirmativo", "requerir", "tercio", "voto", "senador", "formulado", "presente", "moción", "votar", "sírvanse"], ["afirmativo", "tercio", "voto", "formulado", "senador", "presente", "moción", "señor", "votar", "sírvanse"], ["afirmativo", "sírvanse", "indicar", "votar", "resultar", "él", "formulado", "moción", "oliva", "ingreso"], ["tratado", "tabla", "solicitar", "presidente", "señora", "proyecto", "señor", "colón", "tratamiento", "alcanzado"], ["consideración", "nogoyá", "diamante", "gualeguaychú", "nuevamente", "corresponder", "asunto", "lista", "gualeguay", "turno"], ["asunto", "parlamentario", "labor", "acta", "entrado", "resultado", "listo", "votación", "aprobado", "establecido"], ["leído", "desarrollado", "siguiente", "conformar", "alzado", "mano", "votación", "tratamiento", "poner", "acordado"], ["revisión", "aprobado", "honorable", "diputado", "cámara", "quedar", "pasar", "devolver", "plan", "orden"], ["palabra", "departamento", "consideración", "villaguay", "senador", "turno", "victoria", "homenaje", "gualeguaychú", "uruguay"], ["número", "expediente", "acta", "proyecto", "comunicación", "bloque", "declaración", "pendiente", "acordar", "modo"], ["sancionado", "promulgación", "quedar", "ejecutivo", "pasar", "poder", "pertinente", "aprobado", "comunicación", "funcionar"], ["hacer", "poder", "provincia", "proyecto", "él", "ley", "año", "decir", "senador", "querer"]]}, {"Dataset": "/app/own/datasets/senadores", "Dataset Size": 856, "Model": "BERTopic", "Params": {"embedding_model": "all-mpnet-base-v2", "nr_topics": 35, "min_topic_size": 15, "verbose": true, "calculate_probabilities": false}, "Scores": {"cv": 0.5596777732203495, "npmi": 0.23142885085422943, "diversity": 0.5882352941176471}, "Computation Time": 5.46142053604126, "Topics": [["uruguay", "solicitar", "solicitar", "solicitar", "solicitar", "solicitar", "solicitar", "solicitar", "solicitar", "solicitar"], ["diamante", "solicitar", "solicitar", "solicitar", "solicitar", "solicitar", "solicitar", "solicitar", "solicitar", "solicitar"], ["asistencia", "tomar", "así", "secretaría", "hacer", "asentimiento", "verónico", "tarde", "bienvenida", "berisso"], ["reservado", "quedar", "secretaría", "homenaje", "prosecretaría", "asistencia", "tomar", "así", "hacer", "solicitar"], ["tratado", "tabla", "solicitar", "presidente", "señora", "proyecto", "señor", "colón", "tratamiento", "alcanzado"], ["afirmativo", "sírvanse", "indicar", "resultar", "cuerpo", "consideración", "vergaro", "solicitud", "él", "ingreso"], ["afirmativo", "requerir", "tercio", "voto", "senador", "formulado", "presente", "moción", "votar", "sírvanse"], ["afirmativo", "sírvanse", "indicar", "votar", "resultar", "él", "formulado", "moción", "oliva", "ingreso"], ["afirmativo", "tercio", "voto", "formulado", "senador", "presente", "moción", "señor", "votar", "sírvanse"], ["revisión", "aprobado", "honorable", "diputado", "cámara", "quedar", "pasar", "devolver", "plan", "orden"], ["consideración", "federación", "nogoyá", "diamante", "gualeguaychú", "corresponder", "lista", "asunto", "nuevamente", "turno"], ["palabra", "departamento", "consideración", "villaguay", "senador", "turno", "victoria", "homenaje", "gualeguaychú", "uruguay"], ["sancionado", "promulgación", "quedar", "ejecutivo", "pasar", "poder", "pertinente", "aprobado", "comunicación", "orden"], ["acta", "entrado", "resultado", "parlamentario", "labor", "votación", "aprobado", "asunto", "día", "hoy"], ["leído", "desarrollado", "siguiente", "conformar", "alzado", "mano", "votación", "tratamiento", "poner", "acordado"], ["número", "expediente", "acta", "proyecto", "comunicación", "bloque", "declaración", "pendiente", "acordar", "modo"], ["hacer", "poder", "proyecto", "provincia", "él", "ley", "año", "decir", "senador", "querer"]]}, {"Dataset": "/app/own/datasets/senadores", "Dataset Size": 856, "Model": "BERTopic", "Params": {"embedding_model": "all-mpnet-base-v2", "nr_topics": 40, "min_topic_size": 15, "verbose": true, "calculate_probabilities": false}, "Scores": {"cv": 0.5616412020385709, "npmi": 0.220281176734949, "diversity": 0.6}, "Computation Time": 5.344135522842407, "Topics": [["afirmativo", "sírvanse", "indicar", "votar", "resultar", "él", "formulado", "moción", "oliva", "ingreso"], ["diamante", "solicitar", "solicitar", "solicitar", "solicitar", "solicitar", "solicitar", "solicitar", "solicitar", "solicitar"], ["uruguay", "solicitar", "solicitar", "solicitar", "solicitar", "solicitar", "solicitar", "solicitar", "solicitar", "solicitar"], ["afirmativo", "sírvanse", "indicar", "resultar", "cuerpo", "consideración", "vergaro", "solicitud", "él", "ingreso"], ["afirmativo", "requerir", "tercio", "voto", "senador", "formulado", "presente", "moción", "votar", "sírvanse"], ["reservado", "quedar", "secretaría", "homenaje", "prosecretaría", "asistencia", "tomar", "así", "hacer", "solicitar"], ["asistencia", "tomar", "así", "secretaría", "hacer", "asentimiento", "verónico", "tarde", "bienvenida", "berisso"], ["afirmativo", "tercio", "voto", "formulado", "senador", "presente", "moción", "señor", "votar", "sírvanse"], ["tratado", "tabla", "solicitar", "presidente", "señora", "proyecto", "señor", "colón", "tratamiento", "alcanzado"], ["consideración", "nogoyá", "diamante", "gualeguaychú", "nuevamente", "corresponder", "asunto", "lista", "gualeguay", "turno"], ["revisión", "aprobado", "honorable", "diputado", "cámara", "quedar", "pasar", "devolver", "plan", "orden"], ["palabra", "consideración", "departamento", "villaguay", "turno", "federación", "senador", "victoria", "homenaje", "gualeguaychú"], ["sancionado", "promulgación", "quedar", "ejecutivo", "pasar", "poder", "pertinente", "aprobado", "comunicación", "funcionar"], ["número", "expediente", "acta", "proyecto", "comunicación", "bloque", "declaración", "pendiente", "acordar", "modo"], ["hacer", "poder", "provincia", "proyecto", "él", "ley", "año", "decir", "senador", "querer"], ["leído", "desarrollado", "siguiente", "conformar", "alzado", "mano", "votación", "tratamiento", "poner", "acordado"], ["acta", "entrado", "resultado", "parlamentario", "labor", "votación", "aprobado", "asunto", "día", "hoy"]]}, {"Dataset": "/app/own/datasets/senadores", "Dataset Size": 856, "Model": "BERTopic", "Params": {"embedding_model": "all-mpnet-base-v2", "nr_topics": 45, "min_topic_size": 15, "verbose": true, "calculate_probabilities": false}, "Scores": {"cv": 0.5349981091908742, "npmi": 0.19273814788379612, "diversity": 0.5882352941176471}, "Computation Time": 5.194066524505615, "Topics": [["uruguay", "solicitar", "solicitar", "solicitar", "solicitar", "solicitar", "solicitar", "solicitar", "solicitar", "solicitar"], ["diamante", "informado", "afirmativo", "votar", "sírvanse", "indicar", "resultar", "secretaría", "él", "solicitar"], ["afirmativo", "sírvanse", "indicar", "resultar", "cuerpo", "consideración", "vergaro", "solicitud", "él", "ingreso"], ["asistencia", "tomar", "así", "secretaría", "hacer", "asentimiento", "verónico", "tarde", "bienvenida", "berisso"], ["reservado", "quedar", "secretaría", "homenaje", "prosecretaría", "asistencia", "tomar", "así", "hacer", "solicitar"], ["acta", "entrado", "resultado", "parlamentario", "labor", "votación", "aprobado", "asunto", "día", "hoy"], ["parlamentario", "labor", "leído", "desarrollado", "siguiente", "conformar", "alzado", "mano", "votación", "tratamiento"], ["afirmativo", "sírvanse", "indicar", "votar", "resultar", "él", "formulado", "moción", "oliva", "ingreso"], ["afirmativo", "tercio", "voto", "formulado", "senador", "presente", "moción", "señor", "votar", "sírvanse"], ["afirmativo", "requerir", "tercio", "voto", "senador", "formulado", "presente", "moción", "votar", "sírvanse"], ["tratado", "tabla", "solicitar", "presidente", "señora", "proyecto", "señor", "colón", "tratamiento", "alcanzado"], ["revisión", "aprobado", "honorable", "diputado", "cámara", "quedar", "pasar", "devolver", "plan", "orden"], ["consideración", "federación", "nogoyá", "diamante", "gualeguaychú", "corresponder", "lista", "asunto", "nuevamente", "turno"], ["palabra", "departamento", "consideración", "villaguay", "senador", "turno", "victoria", "homenaje", "gualeguaychú", "uruguay"], ["sancionado", "promulgación", "quedar", "ejecutivo", "pasar", "poder", "pertinente", "aprobado", "comunicación", "funcionar"], ["número", "expediente", "acta", "proyecto", "comunicación", "bloque", "declaración", "pendiente", "acordar", "modo"], ["hacer", "poder", "provincia", "proyecto", "ley", "él", "año", "decir", "senador", "querer"]]}, {"Dataset": "/app/own/datasets/senadores", "Dataset Size": 856, "Model": "BERTopic", "Params": {"embedding_model": "all-mpnet-base-v2", "nr_topics": 50, "min_topic_size": 15, "verbose": true, "calculate_probabilities": false}, "Scores": {"cv": 0.5755290742333183, "npmi": 0.2395004026860031, "diversity": 0.5705882352941176}, "Computation Time": 4.642743825912476, "Topics": [["diamante", "solicitar", "solicitar", "solicitar", "solicitar", "solicitar", "solicitar", "solicitar", "solicitar", "solicitar"], ["uruguay", "solicitar", "solicitar", "solicitar", "solicitar", "solicitar", "solicitar", "solicitar", "solicitar", "solicitar"], ["afirmativo", "sírvanse", "indicar", "resultar", "votar", "formulado", "él", "moción", "oliva", "ingreso"], ["afirmativo", "sírvanse", "indicar", "resultar", "cuerpo", "consideración", "vergaro", "solicitud", "él", "ingreso"], ["afirmativo", "requerir", "tercio", "voto", "senador", "formulado", "presente", "moción", "votar", "sírvanse"], ["reservado", "quedar", "secretaría", "homenaje", "solicitar", "solicitar", "solicitar", "solicitar", "solicitar", "solicitar"], ["asistencia", "tomar", "así", "secretaría", "hacer", "prosecretaría", "asentimiento", "quedar", "reservado", "verónico"], ["afirmativo", "tercio", "voto", "senador", "formulado", "presente", "señor", "moción", "votar", "señoro"], ["tratado", "tabla", "solicitar", "presidente", "señora", "proyecto", "señor", "colón", "tratamiento", "alcanzado"], ["consideración", "federación", "nogoyá", "diamante", "gualeguaychú", "corresponder", "lista", "asunto", "nuevamente", "turno"], ["parlamentario", "labor", "leído", "desarrollado", "siguiente", "conformar", "alzado", "mano", "votación", "tratamiento"], ["acta", "entrado", "resultado", "votación", "aprobado", "asunto", "parlamentario", "labor", "día", "hoy"], ["revisión", "aprobado", "honorable", "diputado", "cámara", "quedar", "pasar", "devolver", "plan", "orden"], ["palabra", "departamento", "consideración", "villaguay", "senador", "turno", "victoria", "homenaje", "gualeguaychú", "uruguay"], ["sancionado", "promulgación", "quedar", "ejecutivo", "pasar", "poder", "pertinente", "aprobado", "comunicación", "funcionar"], ["número", "expediente", "acta", "proyecto", "comunicación", "bloque", "declaración", "pendiente", "acordar", "modo"], ["hacer", "poder", "provincia", "proyecto", "ley", "él", "año", "decir", "senador", "querer"]]}]